[{"Time":"4:00 PM","Date":"12/13/2023","Venue_name":"Yerba Buena","Venue_address":"3594 Sundown Crossing","City":"Zipárion","Venue_capacity":350,"Support":"Saving Bob","Price_USD":30},
{"Time":"12:52 PM","Date":"6/29/2023","Venue_name":"False Mountain Willow","Venue_address":"99044 Waubesa Hill","City":"Sobeok","Venue_capacity":143,"Support":"Cool Tooth Fairy Attack","Price_USD":38},
{"Time":"5:10 PM","Date":"12/20/2023","Venue_name":"Santa Rita Mountain Aster","Venue_address":"9 Graedel Pass","City":"Cibugel","Venue_capacity":284,"Support":"Saving Bob","Price_USD":38},
{"Time":"1:16 PM","Date":"8/17/2023","Venue_name":"Blytt's Bryum Moss","Venue_address":"32 Golf Center","City":"Maiyema","Venue_capacity":297,"Support":"Cool Kid Bob","Price_USD":41},
{"Time":"8:12 PM","Date":"11/21/2023","Venue_name":"Sneezeweed","Venue_address":"183 Tony Parkway","City":"Al Azraq ash Shamālī","Venue_capacity":361,"Support":"Flight of the Grey Cockroaches","Price_USD":28},
{"Time":"12:21 PM","Date":"9/3/2023","Venue_name":"Myrtus","Venue_address":"601 Magdeline Trail","City":"Ban Dan","Venue_capacity":448,"Support":"Saving Bob","Price_USD":38},
{"Time":"4:56 PM","Date":"3/24/2023","Venue_name":"Savinleaf Groundpine","Venue_address":"27 Hanson Avenue","City":"Barranca de Upía","Venue_capacity":228,"Support":"Cool Kid Bob","Price_USD":20},
{"Time":"7:46 PM","Date":"5/15/2023","Venue_name":"Northern False Candytuft","Venue_address":"466 Hayes Crossing","City":"Smołdzino","Venue_capacity":329,"Support":"Flight of the Grey Cockroaches","Price_USD":49},
{"Time":"6:21 PM","Date":"12/5/2023","Venue_name":"Sprawling Hoarypea","Venue_address":"992 Park Meadow Avenue","City":"Nihommatsu","Venue_capacity":336,"Support":"Flight of the Grey Cockroaches","Price_USD":25},
{"Time":"6:15 PM","Date":"3/22/2023","Venue_name":"Fivepetal Cliffbush","Venue_address":"88900 Heffernan Road","City":"Lons-le-Saunier","Venue_capacity":69,"Support":"Flight of the Grey Cockroaches","Price_USD":20},
{"Time":"5:18 PM","Date":"5/10/2023","Venue_name":"Coastal Bristlegrass","Venue_address":"71 Brentwood Way","City":"Farroupilha","Venue_capacity":371,"Support":"Cool Tooth Fairy Attack","Price_USD":35},
{"Time":"8:45 PM","Date":"7/2/2023","Venue_name":"Kio'ele","Venue_address":"4 Merry Park","City":"Youhao","Venue_capacity":107,"Support":"Working Oslo","Price_USD":37},
{"Time":"2:04 PM","Date":"5/28/2023","Venue_name":"Littleleaf Brickellbush","Venue_address":"66734 Holmberg Pass","City":"Rumāh","Venue_capacity":197,"Support":"Cool Kid Bob","Price_USD":48},
{"Time":"7:46 PM","Date":"11/5/2023","Venue_name":"Calder's Rockcress","Venue_address":"40940 Portage Way","City":"Pau","Venue_capacity":50,"Support":"Working Oslo","Price_USD":43},
{"Time":"2:11 PM","Date":"6/30/2023","Venue_name":"Rinodina Lichen","Venue_address":"85856 Harper Plaza","City":"Upton","Venue_capacity":318,"Support":"Cool Tooth Fairy Attack","Price_USD":49},
{"Time":"2:49 PM","Date":"2/8/2023","Venue_name":"Quill Sedge","Venue_address":"71 Randy Pass","City":"Tianjiazhai","Venue_capacity":226,"Support":"Working Oslo","Price_USD":42},
{"Time":"12:23 PM","Date":"10/22/2023","Venue_name":"Proliferous Pink","Venue_address":"9 Spenser Pass","City":"Maha Sarakham","Venue_capacity":309,"Support":"Cool Tooth Fairy Attack","Price_USD":28},
{"Time":"12:35 PM","Date":"5/22/2023","Venue_name":"Hairy Cornsalad","Venue_address":"18123 Badeau Hill","City":"Silver Spring","Venue_capacity":92,"Support":"Cool Tooth Fairy Attack","Price_USD":43},
{"Time":"12:50 PM","Date":"1/24/2023","Venue_name":"Alpine Fleabane","Venue_address":"8 Sherman Drive","City":"Quzi","Venue_capacity":442,"Support":"Flight of the Grey Cockroaches","Price_USD":43},
{"Time":"2:24 PM","Date":"1/9/2023","Venue_name":"Narrowleaf Gentian","Venue_address":"56778 Ridgeway Drive","City":"Rzeszów","Venue_capacity":180,"Support":"Cool Kid Bob","Price_USD":47},
{"Time":"7:57 PM","Date":"4/13/2023","Venue_name":"Showy Tarweed","Venue_address":"375 Dapin Circle","City":"Mallow","Venue_capacity":224,"Support":"Cool Tooth Fairy Attack","Price_USD":37},
{"Time":"7:34 PM","Date":"11/28/2023","Venue_name":"Hooker's Milkwort","Venue_address":"178 Bellgrove Hill","City":"Banyulegi","Venue_capacity":164,"Support":"Saving Bob","Price_USD":48},
{"Time":"12:22 PM","Date":"3/14/2023","Venue_name":"Kobus Magnolia","Venue_address":"672 Raven Place","City":"Ambat","Venue_capacity":131,"Support":"Working Oslo","Price_USD":41},
{"Time":"1:09 PM","Date":"5/5/2023","Venue_name":"Tufted Airplant","Venue_address":"1032 Prentice Center","City":"Cláudio","Venue_capacity":306,"Support":"Working Oslo","Price_USD":24},
{"Time":"12:11 PM","Date":"4/22/2023","Venue_name":"Arrow Bamboo","Venue_address":"33687 Calypso Street","City":"Bandar-e Lengeh","Venue_capacity":64,"Support":"Flight of the Grey Cockroaches","Price_USD":41},
{"Time":"4:40 PM","Date":"7/15/2023","Venue_name":"Dust Lichen","Venue_address":"193 Atwood Court","City":"Pakemitan","Venue_capacity":415,"Support":"Flight of the Grey Cockroaches","Price_USD":47},
{"Time":"7:40 PM","Date":"9/1/2023","Venue_name":"Prickly Cryptantha","Venue_address":"28 Vermont Hill","City":"Mranggen","Venue_capacity":402,"Support":"Working Oslo","Price_USD":44},
{"Time":"1:26 PM","Date":"12/14/2023","Venue_name":"Gold-of-pleasure","Venue_address":"1653 Quincy Trail","City":"Xinying","Venue_capacity":384,"Support":"Cool Kid Bob","Price_USD":37},
{"Time":"1:23 PM","Date":"6/17/2023","Venue_name":"Metcalfe's Ticktrefoil","Venue_address":"93 Lakewood Gardens Junction","City":"Léo","Venue_capacity":490,"Support":"Working Oslo","Price_USD":44},
{"Time":"4:59 PM","Date":"9/20/2023","Venue_name":"Igniar's Dotted Lichen","Venue_address":"29 Westerfield Court","City":"Potiskum","Venue_capacity":125,"Support":"Flight of the Grey Cockroaches","Price_USD":46},
{"Time":"1:43 PM","Date":"11/20/2023","Venue_name":"Queen-devil Hawkweed","Venue_address":"995 Pierstorff Trail","City":"Ganyan","Venue_capacity":84,"Support":"Saving Bob","Price_USD":37},
{"Time":"4:42 PM","Date":"9/30/2023","Venue_name":"Hampe's Entodon Moss","Venue_address":"781 Burning Wood Center","City":"Kanluran","Venue_capacity":425,"Support":"Working Oslo","Price_USD":40},
{"Time":"3:46 PM","Date":"6/29/2023","Venue_name":"Jones' Linanthus","Venue_address":"6 Lighthouse Bay Circle","City":"Bogojevo","Venue_capacity":418,"Support":"Cool Kid Bob","Price_USD":25},
{"Time":"7:39 PM","Date":"12/11/2023","Venue_name":"Globe Earth Lichen","Venue_address":"226 Hayes Court","City":"Stepove","Venue_capacity":315,"Support":"Saving Bob","Price_USD":34},
{"Time":"2:06 PM","Date":"7/10/2023","Venue_name":"Western Wild Petunia","Venue_address":"1 Northfield Park","City":"Calumpang","Venue_capacity":275,"Support":"Cool Tooth Fairy Attack","Price_USD":47},
{"Time":"5:11 PM","Date":"3/1/2023","Venue_name":"Rosy Owl's-clover","Venue_address":"055 Troy Lane","City":"Bárrio","Venue_capacity":246,"Support":"Cool Kid Bob","Price_USD":31},
{"Time":"2:38 PM","Date":"2/6/2023","Venue_name":"Neglected Sunflower","Venue_address":"4 Basil Lane","City":"Marieville","Venue_capacity":230,"Support":"Cool Tooth Fairy Attack","Price_USD":26},
{"Time":"4:22 PM","Date":"3/5/2023","Venue_name":"Fishscale Lichen","Venue_address":"31 Bobwhite Point","City":"Emiliano Zapata","Venue_capacity":436,"Support":"Cool Tooth Fairy Attack","Price_USD":46},
{"Time":"7:53 PM","Date":"12/10/2023","Venue_name":"American Nailwort","Venue_address":"6 Hollow Ridge Way","City":"Brejos","Venue_capacity":367,"Support":"Cool Kid Bob","Price_USD":40},
{"Time":"7:20 PM","Date":"11/29/2023","Venue_name":"Bluish Spikemoss","Venue_address":"0417 6th Pass","City":"Thị Trấn Mường Lát","Venue_capacity":435,"Support":"Cool Tooth Fairy Attack","Price_USD":21},
{"Time":"12:16 PM","Date":"8/14/2023","Venue_name":"California Ash","Venue_address":"5319 Porter Junction","City":"Kuanfatu","Venue_capacity":495,"Support":"Saving Bob","Price_USD":23},
{"Time":"12:35 PM","Date":"2/10/2023","Venue_name":"Chestnut","Venue_address":"6528 Oak Valley Alley","City":"Vratsa","Venue_capacity":384,"Support":"Working Oslo","Price_USD":39},
{"Time":"8:07 PM","Date":"7/28/2023","Venue_name":"Arctopeltis Lichen","Venue_address":"82 Portage Alley","City":"Călăraşi","Venue_capacity":247,"Support":"Working Oslo","Price_USD":22},
{"Time":"7:35 PM","Date":"1/31/2023","Venue_name":"Pale Desert Lupine","Venue_address":"5 Northridge Trail","City":"Banjar Swastika","Venue_capacity":238,"Support":"Working Oslo","Price_USD":40},
{"Time":"7:04 PM","Date":"11/12/2023","Venue_name":"Gray's Townsend Daisy","Venue_address":"43 Katie Junction","City":"Nantes","Venue_capacity":419,"Support":"Cool Tooth Fairy Attack","Price_USD":26},
{"Time":"4:00 PM","Date":"6/20/2023","Venue_name":"Claoxylon","Venue_address":"49 Ilene Way","City":"Emiliano Zapata","Venue_capacity":154,"Support":"Working Oslo","Price_USD":48},
{"Time":"12:26 PM","Date":"11/23/2023","Venue_name":"Polyblastia Lichen","Venue_address":"21885 Texas Court","City":"Xianxi","Venue_capacity":232,"Support":"Flight of the Grey Cockroaches","Price_USD":21},
{"Time":"6:42 PM","Date":"5/6/2023","Venue_name":"Coues' Cassia","Venue_address":"75736 Hayes Avenue","City":"Bārah","Venue_capacity":177,"Support":"Working Oslo","Price_USD":26},
{"Time":"6:03 PM","Date":"4/9/2023","Venue_name":"Cutleaf Goosefoot","Venue_address":"623 Vidon Court","City":"Keli","Venue_capacity":360,"Support":"Working Oslo","Price_USD":47},
{"Time":"4:23 PM","Date":"10/18/2023","Venue_name":"Erect Centella","Venue_address":"0 Helena Plaza","City":"Jiudu","Venue_capacity":136,"Support":"Flight of the Grey Cockroaches","Price_USD":32},
{"Time":"5:18 PM","Date":"10/15/2023","Venue_name":"Purplebeak Owl's-clover","Venue_address":"25 Golf View Street","City":"Presa","Venue_capacity":369,"Support":"Saving Bob","Price_USD":50},
{"Time":"12:25 PM","Date":"7/2/2023","Venue_name":"Blessed Thistle","Venue_address":"6826 Clove Park","City":"Bakau","Venue_capacity":123,"Support":"Saving Bob","Price_USD":41},
{"Time":"2:48 PM","Date":"4/1/2023","Venue_name":"Threeleaf Woodsorrel","Venue_address":"2356 Forest Dale Avenue","City":"Cikandang","Venue_capacity":320,"Support":"Flight of the Grey Cockroaches","Price_USD":28},
{"Time":"7:36 PM","Date":"1/20/2023","Venue_name":"Fewseed Sedge","Venue_address":"207 Aberg Plaza","City":"Quilino","Venue_capacity":171,"Support":"Cool Tooth Fairy Attack","Price_USD":32},
{"Time":"3:34 PM","Date":"3/22/2023","Venue_name":"Dwarf Mousetail","Venue_address":"26815 International Trail","City":"Kansas City","Venue_capacity":155,"Support":"Cool Kid Bob","Price_USD":22},
{"Time":"8:44 PM","Date":"6/2/2023","Venue_name":"Birdnest Milkvetch","Venue_address":"5172 Erie Lane","City":"Kizlyar","Venue_capacity":65,"Support":"Cool Tooth Fairy Attack","Price_USD":50},
{"Time":"2:57 PM","Date":"7/8/2023","Venue_name":"Canadian Gooseberry","Venue_address":"94 Sunbrook Hill","City":"Timrå","Venue_capacity":484,"Support":"Cool Kid Bob","Price_USD":31},
{"Time":"12:11 PM","Date":"5/13/2023","Venue_name":"Bitter Root","Venue_address":"9 Laurel Crossing","City":"Gigante","Venue_capacity":418,"Support":"Working Oslo","Price_USD":43},
{"Time":"5:08 PM","Date":"3/1/2023","Venue_name":"Hawkweed","Venue_address":"98117 1st Place","City":"Łapanów","Venue_capacity":353,"Support":"Cool Tooth Fairy Attack","Price_USD":43},
{"Time":"6:53 PM","Date":"6/22/2023","Venue_name":"Ione Buckwheat","Venue_address":"148 Shopko Terrace","City":"Xiaochi","Venue_capacity":434,"Support":"Cool Tooth Fairy Attack","Price_USD":46},
{"Time":"7:00 PM","Date":"8/4/2023","Venue_name":"Wright's Waterwillow","Venue_address":"578 Laurel Court","City":"Волочаевское","Venue_capacity":285,"Support":"Working Oslo","Price_USD":22},
{"Time":"5:08 PM","Date":"12/9/2023","Venue_name":"Bailey's Rabbitbrush","Venue_address":"7714 Ruskin Junction","City":"Belle-Anse","Venue_capacity":257,"Support":"Cool Kid Bob","Price_USD":44},
{"Time":"6:16 PM","Date":"6/3/2023","Venue_name":"Pine Rose","Venue_address":"40340 Little Fleur Trail","City":"Zhongdong","Venue_capacity":246,"Support":"Saving Bob","Price_USD":32},
{"Time":"6:19 PM","Date":"6/10/2023","Venue_name":"Forked Woodrush","Venue_address":"45 Sundown Avenue","City":"Kalamáta","Venue_capacity":334,"Support":"Flight of the Grey Cockroaches","Price_USD":41},
{"Time":"7:00 PM","Date":"7/24/2023","Venue_name":"Little Elephantshead","Venue_address":"283 Esch Alley","City":"Baima","Venue_capacity":336,"Support":"Working Oslo","Price_USD":33},
{"Time":"7:06 PM","Date":"3/14/2023","Venue_name":"Niebla Lichen","Venue_address":"63 Heffernan Hill","City":"Nanding","Venue_capacity":189,"Support":"Saving Bob","Price_USD":41},
{"Time":"12:53 PM","Date":"12/1/2023","Venue_name":"Molokai Ohaha","Venue_address":"8223 Saint Paul Drive","City":"Fort Worth","Venue_capacity":328,"Support":"Saving Bob","Price_USD":50},
{"Time":"1:45 PM","Date":"9/21/2023","Venue_name":"Thistleleaf Aster","Venue_address":"88 Crownhardt Lane","City":"Nanterre","Venue_capacity":322,"Support":"Saving Bob","Price_USD":40},
{"Time":"7:26 PM","Date":"3/7/2023","Venue_name":"Great Blue Lobelia","Venue_address":"8 Manufacturers Hill","City":"Calzada Larga","Venue_capacity":193,"Support":"Working Oslo","Price_USD":39},
{"Time":"12:50 PM","Date":"3/17/2023","Venue_name":"Wax Mallow","Venue_address":"8902 Mcbride Terrace","City":"Zhiqu","Venue_capacity":111,"Support":"Cool Kid Bob","Price_USD":29},
{"Time":"3:58 PM","Date":"11/1/2023","Venue_name":"Hardheads","Venue_address":"2571 Haas Way","City":"Kolonnawa","Venue_capacity":328,"Support":"Working Oslo","Price_USD":35},
{"Time":"2:19 PM","Date":"12/20/2023","Venue_name":"Dogtongue Buckwheat","Venue_address":"28 Amoth Court","City":"San Isidro","Venue_capacity":305,"Support":"Saving Bob","Price_USD":21},
{"Time":"7:20 PM","Date":"10/5/2023","Venue_name":"New York Aster","Venue_address":"536 Lighthouse Bay Avenue","City":"Tingloy","Venue_capacity":281,"Support":"Cool Kid Bob","Price_USD":47},
{"Time":"4:51 PM","Date":"3/21/2023","Venue_name":"Royal Poinciana","Venue_address":"14 Grim Parkway","City":"Sulūk","Venue_capacity":82,"Support":"Working Oslo","Price_USD":31},
{"Time":"1:05 PM","Date":"1/27/2023","Venue_name":"Bahia","Venue_address":"397 Nevada Street","City":"Pakkat","Venue_capacity":317,"Support":"Cool Tooth Fairy Attack","Price_USD":27},
{"Time":"2:36 PM","Date":"5/1/2023","Venue_name":"Luehea","Venue_address":"3 Dorton Crossing","City":"Patquía","Venue_capacity":453,"Support":"Saving Bob","Price_USD":33},
{"Time":"2:04 PM","Date":"4/7/2023","Venue_name":"Sea Clover","Venue_address":"1848 Pankratz Circle","City":"Jianghai","Venue_capacity":496,"Support":"Saving Bob","Price_USD":20},
{"Time":"6:34 PM","Date":"3/12/2023","Venue_name":"Laguncularia","Venue_address":"64241 Upham Center","City":"Zhongfan","Venue_capacity":92,"Support":"Cool Tooth Fairy Attack","Price_USD":46},
{"Time":"8:25 PM","Date":"10/14/2023","Venue_name":"Lakeside Sunflower","Venue_address":"018 Farmco Park","City":"Celica","Venue_capacity":291,"Support":"Saving Bob","Price_USD":30},
{"Time":"4:32 PM","Date":"9/16/2023","Venue_name":"Beet","Venue_address":"108 Elmside Parkway","City":"Terpsithéa","Venue_capacity":336,"Support":"Flight of the Grey Cockroaches","Price_USD":26},
{"Time":"4:22 PM","Date":"5/21/2023","Venue_name":"Slender Aster","Venue_address":"54797 Sunbrook Place","City":"Changqiao","Venue_capacity":115,"Support":"Saving Bob","Price_USD":34},
{"Time":"4:37 PM","Date":"11/13/2023","Venue_name":"Shasta Knotweed","Venue_address":"99 Dunning Lane","City":"Xinan","Venue_capacity":292,"Support":"Cool Tooth Fairy Attack","Price_USD":29},
{"Time":"8:11 PM","Date":"7/12/2023","Venue_name":"Virola","Venue_address":"7 Pleasure Court","City":"Słubice","Venue_capacity":372,"Support":"Cool Tooth Fairy Attack","Price_USD":32},
{"Time":"7:50 PM","Date":"9/17/2023","Venue_name":"Gall Of The Earth","Venue_address":"9137 Independence Point","City":"Baiyashi","Venue_capacity":443,"Support":"Working Oslo","Price_USD":37},
{"Time":"3:22 PM","Date":"5/11/2023","Venue_name":"Maui Lobelia","Venue_address":"1 Stone Corner Junction","City":"Kebon","Venue_capacity":129,"Support":"Cool Tooth Fairy Attack","Price_USD":41},
{"Time":"2:20 PM","Date":"9/29/2023","Venue_name":"Wild Plantain","Venue_address":"5 Randy Park","City":"Jaruco","Venue_capacity":317,"Support":"Flight of the Grey Cockroaches","Price_USD":24},
{"Time":"7:26 PM","Date":"3/24/2023","Venue_name":"Horsetail","Venue_address":"3874 Green Ridge Pass","City":"Shireet","Venue_capacity":105,"Support":"Working Oslo","Price_USD":40},
{"Time":"5:42 PM","Date":"12/24/2023","Venue_name":"Treasureflower","Venue_address":"84 Fordem Circle","City":"Dzwola","Venue_capacity":93,"Support":"Flight of the Grey Cockroaches","Price_USD":39},
{"Time":"2:11 PM","Date":"2/18/2023","Venue_name":"Mckelvey's Beeblossom","Venue_address":"9902 Gerald Avenue","City":"Xiaozhen","Venue_capacity":118,"Support":"Flight of the Grey Cockroaches","Price_USD":48},
{"Time":"2:59 PM","Date":"5/28/2023","Venue_name":"Bellisima Grande","Venue_address":"2 Novick Lane","City":"Xigebi","Venue_capacity":305,"Support":"Flight of the Grey Cockroaches","Price_USD":31},
{"Time":"1:08 PM","Date":"5/17/2023","Venue_name":"Yellow Archangel","Venue_address":"4 Farwell Point","City":"Dongtundu","Venue_capacity":350,"Support":"Cool Kid Bob","Price_USD":47},
{"Time":"5:40 PM","Date":"8/3/2023","Venue_name":"Senita Cactus","Venue_address":"3 Norway Maple Road","City":"Butwāl","Venue_capacity":51,"Support":"Cool Tooth Fairy Attack","Price_USD":37},
{"Time":"2:59 PM","Date":"6/10/2023","Venue_name":"Sausage Tree","Venue_address":"3182 Knutson Plaza","City":"Touzao","Venue_capacity":247,"Support":"Flight of the Grey Cockroaches","Price_USD":36},
{"Time":"8:21 PM","Date":"11/18/2023","Venue_name":"California Mistmaiden","Venue_address":"03 Mariners Cove Trail","City":"Gorna Oryakhovitsa","Venue_capacity":349,"Support":"Flight of the Grey Cockroaches","Price_USD":20},
{"Time":"4:35 PM","Date":"10/25/2023","Venue_name":"Winter Creeper","Venue_address":"861 Carberry Street","City":"Penelas","Venue_capacity":410,"Support":"Flight of the Grey Cockroaches","Price_USD":30},
{"Time":"7:43 PM","Date":"1/11/2023","Venue_name":"Oblong Bluecurls","Venue_address":"5352 Sutteridge Drive","City":"Borisovka","Venue_capacity":417,"Support":"Saving Bob","Price_USD":20},
{"Time":"2:40 PM","Date":"11/28/2023","Venue_name":"Swamp Milkweed","Venue_address":"0334 Stuart Street","City":"Empangeni","Venue_capacity":430,"Support":"Working Oslo","Price_USD":42},
{"Time":"5:35 PM","Date":"4/19/2023","Venue_name":"Dirina Lichen","Venue_address":"3 Lyons Center","City":"Kastornoye","Venue_capacity":208,"Support":"Cool Kid Bob","Price_USD":44},
{"Time":"2:31 PM","Date":"5/10/2023","Venue_name":"Wolf Lichen","Venue_address":"77905 Ludington Parkway","City":"Löddeköpinge","Venue_capacity":115,"Support":"Saving Bob","Price_USD":35},
{"Time":"8:02 PM","Date":"11/25/2023","Venue_name":"White Rimmed Lichen","Venue_address":"334 Miller Crossing","City":"Qianjia","Venue_capacity":174,"Support":"Saving Bob","Price_USD":33}]